[
  {
    "kind": "Listing",
    "data": {
      "modhash": "",
      "children": [
        {
          "kind": "t3",
          "data": {
            "domain": "self.Bitcoin",
            "banned_by": null,
            "media_embed": {},
            "subreddit": "Bitcoin",
            "selftext_html": "&lt;!-- SC_OFF --&gt;&lt;div class=\"md\"&gt;&lt;p&gt;&lt;a href=\"http://youtu.be/WdrSP0V-KLg?list=PLyJG8cKCy6YcjxSE7ZvGwpdWClBNBOENk\"&gt;http://youtu.be/WdrSP0V-KLg?list=PLyJG8cKCy6YcjxSE7ZvGwpdWClBNBOENk&lt;/a&gt;&lt;/p&gt;\n&lt;/div&gt;&lt;!-- SC_ON --&gt;",
            "selftext": "http://youtu.be/WdrSP0V-KLg?list=PLyJG8cKCy6YcjxSE7ZvGwpdWClBNBOENk",
            "likes": null,
            "user_reports": [],
            "secure_media": null,
            "link_flair_text": null,
            "id": "2ify0d",
            "gilded": 0,
            "secure_media_embed": {},
            "clicked": false,
            "report_reasons": null,
            "author": "Nightshdr",
            "media": null,
            "score": 3,
            "approved_by": null,
            "over_18": false,
            "hidden": false,
            "thumbnail": "self",
            "subreddit_id": "t5_2s3qj",
            "edited": false,
            "link_flair_css_class": null,
            "author_flair_css_class": null,
            "downs": 0,
            "mod_reports": [],
            "saved": false,
            "is_self": true,
            "name": "t3_2ify0d",
            "permalink": "/r/Bitcoin/comments/2ify0d/i_love_my_bitcoins/",
            "stickied": false,
            "created": 1412628054,
            "url": "http://www.reddit.com/r/Bitcoin/comments/2ify0d/i_love_my_bitcoins/",
            "author_flair_text": null,
            "title": "I love my bitcoins!",
            "created_utc": 1412599254,
            "ups": 3,
            "upvote_ratio": 0.72,
            "num_comments": 2,
            "visited": false,
            "num_reports": null,
            "distinguished": null
          }
        }
      ],
      "after": null,
      "before": null
    }
  },
  {
    "kind": "Listing",
    "data": {
      "modhash": "",
      "children": [
        {
          "kind": "t1",
          "data": {
            "subreddit_id": "t5_2s3qj",
            "banned_by": null,
            "link_id": "t3_2ify0d",
            "likes": null,
            "replies": "",
            "user_reports": [],
            "saved": false,
            "id": "cl1u06l",
            "gilded": 0,
            "report_reasons": null,
            "author": "JuliusCaesar108",
            "parent_id": "t3_2ify0d",
            "score": 2,
            "approved_by": null,
            "controversiality": 0,
            "body": "Hey - thanks for putting this up.  Did you upload the video on YouTube?  Anyways, I helped share this by placing this on /r/BitcoinTV to get the word out. ",
            "edited": false,
            "author_flair_css_class": null,
            "downs": 0,
            "body_html": "&lt;div class=\"md\"&gt;&lt;p&gt;Hey - thanks for putting this up.  Did you upload the video on YouTube?  Anyways, I helped share this by placing this on &lt;a href=\"/r/BitcoinTV\"&gt;/r/BitcoinTV&lt;/a&gt; to get the word out. &lt;/p&gt;\n&lt;/div&gt;",
            "subreddit": "Bitcoin",
            "score_hidden": false,
            "name": "t1_cl1u06l",
            "created": 1412630015,
            "author_flair_text": null,
            "created_utc": 1412601215,
            "distinguished": null,
            "mod_reports": [],
            "num_reports": null,
            "ups": 2
          }
        },
        {
          "kind": "t1",
          "data": {
            "subreddit_id": "t5_2s3qj",
            "banned_by": null,
            "link_id": "t3_2ify0d",
            "likes": null,
            "replies": "",
            "user_reports": [],
            "saved": false,
            "id": "cl1v6kw",
            "gilded": 0,
            "report_reasons": null,
            "author": "Nightshdr",
            "parent_id": "t3_2ify0d",
            "score": 1,
            "approved_by": null,
            "controversiality": 0,
            "body": "It was already there but stumbled upon it and enjoyed. It's good to share this, thank you!",
            "edited": false,
            "author_flair_css_class": null,
            "downs": 0,
            "body_html": "&lt;div class=\"md\"&gt;&lt;p&gt;It was already there but stumbled upon it and enjoyed. It&amp;#39;s good to share this, thank you!&lt;/p&gt;\n&lt;/div&gt;",
            "subreddit": "Bitcoin",
            "score_hidden": false,
            "name": "t1_cl1v6kw",
            "created": 1412633361,
            "author_flair_text": null,
            "created_utc": 1412604561,
            "distinguished": null,
            "mod_reports": [],
            "num_reports": null,
            "ups": 1
          }
        }
      ],
      "after": null,
      "before": null
    }
  }
]