[
  {
    "kind": "Listing",
    "data": {
      "modhash": "",
      "children": [
        {
          "kind": "t3",
          "data": {
            "domain": "self.Bitcoin",
            "banned_by": null,
            "media_embed": {},
            "subreddit": "Bitcoin",
            "selftext_html": "&lt;!-- SC_OFF --&gt;&lt;div class=\"md\"&gt;&lt;p&gt;There are exchanges of all kind advertising altcoins. They use bots to make profit causing people to lose money. Overtime people have lost interest in BTC after they lost money in those exchanges.&lt;/p&gt;\n\n&lt;p&gt;&lt;a href=\"http://bitcoinpricelive.com/chinese-bitcoins-crash-market/\"&gt;http://bitcoinpricelive.com/chinese-bitcoins-crash-market/&lt;/a&gt;&lt;/p&gt;\n\n&lt;p&gt;If altcoins didn&amp;#39;t exist BTC wouldn&amp;#39;t be where it is today.&lt;/p&gt;\n\n&lt;p&gt;Thoughts?&lt;/p&gt;\n&lt;/div&gt;&lt;!-- SC_ON --&gt;",
            "selftext": "There are exchanges of all kind advertising altcoins. They use bots to make profit causing people to lose money. Overtime people have lost interest in BTC after they lost money in those exchanges.\n\nhttp://bitcoinpricelive.com/chinese-bitcoins-crash-market/\n\nIf altcoins didn't exist BTC wouldn't be where it is today.\n\nThoughts?",
            "likes": null,
            "user_reports": [],
            "secure_media": null,
            "link_flair_text": null,
            "id": "2igzri",
            "gilded": 0,
            "secure_media_embed": {},
            "clicked": false,
            "report_reasons": null,
            "author": "unusualfacts30",
            "media": null,
            "score": 0,
            "approved_by": null,
            "over_18": false,
            "hidden": false,
            "thumbnail": "self",
            "subreddit_id": "t5_2s3qj",
            "edited": 1412620864,
            "link_flair_css_class": null,
            "author_flair_css_class": null,
            "downs": 0,
            "mod_reports": [],
            "saved": false,
            "is_self": true,
            "name": "t3_2igzri",
            "permalink": "/r/Bitcoin/comments/2igzri/does_anyone_think_exchanges_play_a_big_role_on/",
            "stickied": false,
            "created": 1412649175,
            "url": "http://www.reddit.com/r/Bitcoin/comments/2igzri/does_anyone_think_exchanges_play_a_big_role_on/",
            "author_flair_text": null,
            "title": "Does anyone think exchanges play a big role on this crash?",
            "created_utc": 1412620375,
            "ups": 0,
            "upvote_ratio": 0.44,
            "num_comments": 4,
            "visited": false,
            "num_reports": null,
            "distinguished": null
          }
        }
      ],
      "after": null,
      "before": null
    }
  },
  {
    "kind": "Listing",
    "data": {
      "modhash": "",
      "children": [
        {
          "kind": "t1",
          "data": {
            "subreddit_id": "t5_2s3qj",
            "banned_by": null,
            "link_id": "t3_2igzri",
            "likes": null,
            "replies": {
              "kind": "Listing",
              "data": {
                "modhash": "",
                "children": [
                  {
                    "kind": "t1",
                    "data": {
                      "subreddit_id": "t5_2s3qj",
                      "banned_by": null,
                      "link_id": "t3_2igzri",
                      "likes": null,
                      "replies": {
                        "kind": "Listing",
                        "data": {
                          "modhash": "",
                          "children": [
                            {
                              "kind": "t1",
                              "data": {
                                "subreddit_id": "t5_2s3qj",
                                "banned_by": null,
                                "link_id": "t3_2igzri",
                                "likes": null,
                                "replies": {
                                  "kind": "Listing",
                                  "data": {
                                    "modhash": "",
                                    "children": [
                                      {
                                        "kind": "t1",
                                        "data": {
                                          "subreddit_id": "t5_2s3qj",
                                          "banned_by": null,
                                          "link_id": "t3_2igzri",
                                          "likes": null,
                                          "replies": "",
                                          "user_reports": [],
                                          "saved": false,
                                          "id": "cl23zhw",
                                          "gilded": 0,
                                          "report_reasons": null,
                                          "author": "unusualfacts30",
                                          "parent_id": "t1_cl23rm7",
                                          "score": 1,
                                          "approved_by": null,
                                          "controversiality": 0,
                                          "body": "https://www.google.com/trends/explore#q=bitcoin\n\n\n",
                                          "edited": false,
                                          "author_flair_css_class": null,
                                          "downs": 0,
                                          "body_html": "&lt;div class=\"md\"&gt;&lt;p&gt;&lt;a href=\"https://www.google.com/trends/explore#q=bitcoin\"&gt;https://www.google.com/trends/explore#q=bitcoin&lt;/a&gt;&lt;/p&gt;\n&lt;/div&gt;",
                                          "subreddit": "Bitcoin",
                                          "score_hidden": false,
                                          "name": "t1_cl23zhw",
                                          "created": 1412651389,
                                          "author_flair_text": null,
                                          "created_utc": 1412622589,
                                          "ups": 1,
                                          "mod_reports": [],
                                          "num_reports": null,
                                          "distinguished": null
                                        }
                                      }
                                    ],
                                    "after": null,
                                    "before": null
                                  }
                                },
                                "user_reports": [],
                                "saved": false,
                                "id": "cl23rm7",
                                "gilded": 0,
                                "report_reasons": null,
                                "author": "TimeTravelled",
                                "parent_id": "t1_cl23hik",
                                "score": 0,
                                "approved_by": null,
                                "controversiality": 0,
                                "body": "&gt;lose interest?\n\nI'm sorry sir, I don't really get what you're getting at with this.\n\nBitcoin's community is still expanding.",
                                "edited": false,
                                "author_flair_css_class": null,
                                "downs": 0,
                                "body_html": "&lt;div class=\"md\"&gt;&lt;blockquote&gt;\n&lt;p&gt;lose interest?&lt;/p&gt;\n&lt;/blockquote&gt;\n\n&lt;p&gt;I&amp;#39;m sorry sir, I don&amp;#39;t really get what you&amp;#39;re getting at with this.&lt;/p&gt;\n\n&lt;p&gt;Bitcoin&amp;#39;s community is still expanding.&lt;/p&gt;\n&lt;/div&gt;",
                                "subreddit": "Bitcoin",
                                "score_hidden": false,
                                "name": "t1_cl23rm7",
                                "created": 1412650967,
                                "author_flair_text": null,
                                "created_utc": 1412622167,
                                "distinguished": null,
                                "mod_reports": [],
                                "num_reports": null,
                                "ups": 0
                              }
                            }
                          ],
                          "after": null,
                          "before": null
                        }
                      },
                      "user_reports": [],
                      "saved": false,
                      "id": "cl23hik",
                      "gilded": 0,
                      "report_reasons": null,
                      "author": "unusualfacts30",
                      "parent_id": "t1_cl22yz8",
                      "score": 1,
                      "approved_by": null,
                      "controversiality": 0,
                      "body": "Real loss of BTC is when consumers lose interest. It's not when whale crashes. BTC has been on downtrend for a while now.",
                      "edited": false,
                      "author_flair_css_class": null,
                      "downs": 0,
                      "body_html": "&lt;div class=\"md\"&gt;&lt;p&gt;Real loss of BTC is when consumers lose interest. It&amp;#39;s not when whale crashes. BTC has been on downtrend for a while now.&lt;/p&gt;\n&lt;/div&gt;",
                      "subreddit": "Bitcoin",
                      "score_hidden": false,
                      "name": "t1_cl23hik",
                      "created": 1412650434,
                      "author_flair_text": null,
                      "created_utc": 1412621634,
                      "ups": 1,
                      "mod_reports": [],
                      "num_reports": null,
                      "distinguished": null
                    }
                  }
                ],
                "after": null,
                "before": null
              }
            },
            "user_reports": [],
            "saved": false,
            "id": "cl22yz8",
            "gilded": 0,
            "report_reasons": null,
            "author": "TimeTravelled",
            "parent_id": "t3_2igzri",
            "score": 0,
            "approved_by": null,
            "controversiality": 0,
            "body": "Go read anything rather than wildly shooting your FUD ok?\n\nSome guy with a lot of coin just put up sell walls, end of story.",
            "edited": false,
            "author_flair_css_class": null,
            "downs": 0,
            "body_html": "&lt;div class=\"md\"&gt;&lt;p&gt;Go read anything rather than wildly shooting your FUD ok?&lt;/p&gt;\n\n&lt;p&gt;Some guy with a lot of coin just put up sell walls, end of story.&lt;/p&gt;\n&lt;/div&gt;",
            "subreddit": "Bitcoin",
            "score_hidden": false,
            "name": "t1_cl22yz8",
            "created": 1412649445,
            "author_flair_text": null,
            "created_utc": 1412620645,
            "distinguished": null,
            "mod_reports": [],
            "num_reports": null,
            "ups": 0
          }
        }
      ],
      "after": null,
      "before": null
    }
  }
]