[
  {
    "kind": "Listing",
    "data": {
      "modhash": "",
      "children": [
        {
          "kind": "t3",
          "data": {
            "domain": "self.Bitcoin",
            "banned_by": null,
            "media_embed": {},
            "subreddit": "Bitcoin",
            "selftext_html": "&lt;!-- SC_OFF --&gt;&lt;div class=\"md\"&gt;&lt;p&gt;I signed up for a Circle account the other day.  I&amp;#39;m curious, and I wanted to check them out.  I linked a bank account, and they made their deposits.  When I went to verify, however, I was told &amp;quot;Incorrect Deposit Amount.&amp;quot;  I &lt;em&gt;know&lt;/em&gt; that I was putting in the correct amounts.&lt;/p&gt;\n\n&lt;p&gt;I decided to wait a day and give it another shot.  Also, they had withdrawn the original deposit amounts from my account, which according to their website:&lt;/p&gt;\n\n&lt;p&gt;&lt;strong&gt;Once you verify your bank account, Circle will withdraw those two small amounts from your bank account.&lt;/strong&gt;&lt;/p&gt;\n\n&lt;p&gt;However, when I signed back into my account, there was still no bank account, and no verify link anymore.  I emailed their support team, and received an auto &amp;quot;We&amp;#39;ll get back to you soon...&amp;quot; reply.  Shortly afterwards, I received an email reminding me to verify my account... Still nothing there, and still no reply from the support team.&lt;/p&gt;\n\n&lt;p&gt;Any one else have difficulties with this yet?&lt;/p&gt;\n\n&lt;p&gt;Edit: Formatting...&lt;/p&gt;\n&lt;/div&gt;&lt;!-- SC_ON --&gt;",
            "selftext": "I signed up for a Circle account the other day.  I'm curious, and I wanted to check them out.  I linked a bank account, and they made their deposits.  When I went to verify, however, I was told \"Incorrect Deposit Amount.\"  I *know* that I was putting in the correct amounts.\n\nI decided to wait a day and give it another shot.  Also, they had withdrawn the original deposit amounts from my account, which according to their website:\n\n**Once you verify your bank account, Circle will withdraw those two small amounts from your bank account.**\n\nHowever, when I signed back into my account, there was still no bank account, and no verify link anymore.  I emailed their support team, and received an auto \"We'll get back to you soon...\" reply.  Shortly afterwards, I received an email reminding me to verify my account... Still nothing there, and still no reply from the support team.\n\nAny one else have difficulties with this yet?\n\nEdit: Formatting...",
            "likes": null,
            "user_reports": [],
            "secure_media": null,
            "link_flair_text": null,
            "id": "2i87e4",
            "gilded": 0,
            "secure_media_embed": {},
            "clicked": false,
            "report_reasons": null,
            "author": "aminarcen",
            "media": null,
            "score": 5,
            "approved_by": null,
            "over_18": false,
            "hidden": false,
            "thumbnail": "self",
            "subreddit_id": "t5_2s3qj",
            "edited": false,
            "link_flair_css_class": null,
            "author_flair_css_class": null,
            "downs": 0,
            "mod_reports": [],
            "saved": false,
            "is_self": true,
            "name": "t3_2i87e4",
            "permalink": "/r/Bitcoin/comments/2i87e4/off_to_a_bad_start_with_circle/",
            "stickied": false,
            "created": 1412402472,
            "url": "http://www.reddit.com/r/Bitcoin/comments/2i87e4/off_to_a_bad_start_with_circle/",
            "author_flair_text": null,
            "title": "Off to a Bad Start with Circle",
            "created_utc": 1412373672,
            "ups": 5,
            "upvote_ratio": 0.64,
            "num_comments": 9,
            "visited": false,
            "num_reports": null,
            "distinguished": null
          }
        }
      ],
      "after": null,
      "before": null
    }
  },
  {
    "kind": "Listing",
    "data": {
      "modhash": "",
      "children": [
        {
          "kind": "t1",
          "data": {
            "subreddit_id": "t5_2s3qj",
            "banned_by": null,
            "link_id": "t3_2i87e4",
            "likes": null,
            "replies": {
              "kind": "Listing",
              "data": {
                "modhash": "",
                "children": [
                  {
                    "kind": "t1",
                    "data": {
                      "subreddit_id": "t5_2s3qj",
                      "banned_by": null,
                      "link_id": "t3_2i87e4",
                      "likes": null,
                      "replies": "",
                      "user_reports": [],
                      "saved": false,
                      "id": "ckzr44c",
                      "gilded": 0,
                      "report_reasons": null,
                      "author": "aminarcen",
                      "parent_id": "t1_ckzqzqf",
                      "score": 2,
                      "approved_by": null,
                      "controversiality": 0,
                      "body": "I did. I tried it both ways, with and without the preceding zero.  I can't do anything else at this point, as my bank account doesn't even show up anymore.  I'd just like some confirmation from them regarding what happened before I try to relink it, or just cancel my account and walk away.",
                      "edited": false,
                      "author_flair_css_class": null,
                      "downs": 0,
                      "body_html": "&lt;div class=\"md\"&gt;&lt;p&gt;I did. I tried it both ways, with and without the preceding zero.  I can&amp;#39;t do anything else at this point, as my bank account doesn&amp;#39;t even show up anymore.  I&amp;#39;d just like some confirmation from them regarding what happened before I try to relink it, or just cancel my account and walk away.&lt;/p&gt;\n&lt;/div&gt;",
                      "subreddit": "Bitcoin",
                      "score_hidden": false,
                      "name": "t1_ckzr44c",
                      "created": 1412402943,
                      "author_flair_text": null,
                      "created_utc": 1412374143,
                      "ups": 2,
                      "mod_reports": [],
                      "num_reports": null,
                      "distinguished": null
                    }
                  }
                ],
                "after": null,
                "before": null
              }
            },
            "user_reports": [],
            "saved": false,
            "id": "ckzqzqf",
            "gilded": 0,
            "report_reasons": null,
            "author": "LeoPanthera",
            "parent_id": "t3_2i87e4",
            "score": 2,
            "approved_by": null,
            "controversiality": 0,
            "body": "Did you try putting in the amounts the other way around? And make sure you're entering \"0.xx\" and not just \"xx\". Mine went through first time.",
            "edited": false,
            "author_flair_css_class": null,
            "downs": 0,
            "body_html": "&lt;div class=\"md\"&gt;&lt;p&gt;Did you try putting in the amounts the other way around? And make sure you&amp;#39;re entering &amp;quot;0.xx&amp;quot; and not just &amp;quot;xx&amp;quot;. Mine went through first time.&lt;/p&gt;\n&lt;/div&gt;",
            "subreddit": "Bitcoin",
            "score_hidden": false,
            "name": "t1_ckzqzqf",
            "created": 1412402657,
            "author_flair_text": null,
            "created_utc": 1412373857,
            "distinguished": null,
            "mod_reports": [],
            "num_reports": null,
            "ups": 2
          }
        },
        {
          "kind": "t1",
          "data": {
            "subreddit_id": "t5_2s3qj",
            "banned_by": null,
            "link_id": "t3_2i87e4",
            "likes": null,
            "replies": "",
            "user_reports": [],
            "saved": false,
            "id": "ckzrjf5",
            "gilded": 0,
            "report_reasons": null,
            "author": "toliro",
            "parent_id": "t3_2i87e4",
            "score": 2,
            "approved_by": null,
            "controversiality": 0,
            "body": "Same thing happened to me. Circle has a problem. I added my bank info again, they deposited again, they withdrew again. But the second time the verification did work",
            "edited": false,
            "author_flair_css_class": null,
            "downs": 0,
            "body_html": "&lt;div class=\"md\"&gt;&lt;p&gt;Same thing happened to me. Circle has a problem. I added my bank info again, they deposited again, they withdrew again. But the second time the verification did work&lt;/p&gt;\n&lt;/div&gt;",
            "subreddit": "Bitcoin",
            "score_hidden": false,
            "name": "t1_ckzrjf5",
            "created": 1412403923,
            "author_flair_text": null,
            "created_utc": 1412375123,
            "distinguished": null,
            "mod_reports": [],
            "num_reports": null,
            "ups": 2
          }
        },
        {
          "kind": "t1",
          "data": {
            "subreddit_id": "t5_2s3qj",
            "banned_by": null,
            "link_id": "t3_2i87e4",
            "likes": null,
            "replies": "",
            "user_reports": [],
            "saved": false,
            "id": "ckzs7yt",
            "gilded": 0,
            "report_reasons": null,
            "author": "livefromheaven",
            "parent_id": "t3_2i87e4",
            "score": 2,
            "approved_by": null,
            "controversiality": 0,
            "body": "Exact same story here.  I just tried adding my bank account again - I think someone said their spam policy was set to strictly.  ",
            "edited": false,
            "author_flair_css_class": null,
            "downs": 0,
            "body_html": "&lt;div class=\"md\"&gt;&lt;p&gt;Exact same story here.  I just tried adding my bank account again - I think someone said their spam policy was set to strictly.  &lt;/p&gt;\n&lt;/div&gt;",
            "subreddit": "Bitcoin",
            "score_hidden": false,
            "name": "t1_ckzs7yt",
            "created": 1412405519,
            "author_flair_text": null,
            "created_utc": 1412376719,
            "distinguished": null,
            "mod_reports": [],
            "num_reports": null,
            "ups": 2
          }
        },
        {
          "kind": "t1",
          "data": {
            "subreddit_id": "t5_2s3qj",
            "banned_by": null,
            "link_id": "t3_2i87e4",
            "likes": null,
            "replies": "",
            "user_reports": [],
            "saved": false,
            "id": "ckzu22i",
            "gilded": 0,
            "report_reasons": null,
            "author": "anon515",
            "parent_id": "t3_2i87e4",
            "score": 2,
            "approved_by": null,
            "controversiality": 0,
            "body": "Exact same issue. I'm still waiting for a response, and I don't want to put my bank info twice.",
            "edited": false,
            "author_flair_css_class": null,
            "downs": 0,
            "body_html": "&lt;div class=\"md\"&gt;&lt;p&gt;Exact same issue. I&amp;#39;m still waiting for a response, and I don&amp;#39;t want to put my bank info twice.&lt;/p&gt;\n&lt;/div&gt;",
            "subreddit": "Bitcoin",
            "score_hidden": false,
            "name": "t1_ckzu22i",
            "created": 1412409965,
            "author_flair_text": null,
            "created_utc": 1412381165,
            "distinguished": null,
            "mod_reports": [],
            "num_reports": null,
            "ups": 2
          }
        },
        {
          "kind": "t1",
          "data": {
            "subreddit_id": "t5_2s3qj",
            "banned_by": null,
            "link_id": "t3_2i87e4",
            "likes": null,
            "replies": {
              "kind": "Listing",
              "data": {
                "modhash": "",
                "children": [
                  {
                    "kind": "t1",
                    "data": {
                      "subreddit_id": "t5_2s3qj",
                      "banned_by": null,
                      "link_id": "t3_2i87e4",
                      "likes": null,
                      "replies": "",
                      "user_reports": [],
                      "saved": false,
                      "id": "cl04vw3",
                      "gilded": 0,
                      "report_reasons": null,
                      "author": "aminarcen",
                      "parent_id": "t1_ckzvddl",
                      "score": 1,
                      "approved_by": null,
                      "controversiality": 0,
                      "body": "I did, yes.  I entered them every way possible.  What's funny to me, is that what you said worked for you is the exact opposite of what /u/LeoPanthera said worked for him.  I'd just like a reply back from Circle at this point.",
                      "edited": false,
                      "author_flair_css_class": null,
                      "downs": 0,
                      "body_html": "&lt;div class=\"md\"&gt;&lt;p&gt;I did, yes.  I entered them every way possible.  What&amp;#39;s funny to me, is that what you said worked for you is the exact opposite of what &lt;a href=\"/u/LeoPanthera\"&gt;/u/LeoPanthera&lt;/a&gt; said worked for him.  I&amp;#39;d just like a reply back from Circle at this point.&lt;/p&gt;\n&lt;/div&gt;",
                      "subreddit": "Bitcoin",
                      "score_hidden": false,
                      "name": "t1_cl04vw3",
                      "created": 1412452111,
                      "author_flair_text": null,
                      "created_utc": 1412423311,
                      "ups": 1,
                      "mod_reports": [],
                      "num_reports": null,
                      "distinguished": null
                    }
                  }
                ],
                "after": null,
                "before": null
              }
            },
            "user_reports": [],
            "saved": false,
            "id": "ckzvddl",
            "gilded": 0,
            "report_reasons": null,
            "author": "ardvarkr",
            "parent_id": "t3_2i87e4",
            "score": 2,
            "approved_by": null,
            "controversiality": 0,
            "body": "Did you try entering the amounts as whole numbers? When I entered 0.53, it said incorrect, then I tried 53 and it worked.",
            "edited": false,
            "author_flair_css_class": null,
            "downs": 0,
            "body_html": "&lt;div class=\"md\"&gt;&lt;p&gt;Did you try entering the amounts as whole numbers? When I entered 0.53, it said incorrect, then I tried 53 and it worked.&lt;/p&gt;\n&lt;/div&gt;",
            "subreddit": "Bitcoin",
            "score_hidden": false,
            "name": "t1_ckzvddl",
            "created": 1412413396,
            "author_flair_text": null,
            "created_utc": 1412384596,
            "distinguished": null,
            "mod_reports": [],
            "num_reports": null,
            "ups": 2
          }
        },
        {
          "kind": "t1",
          "data": {
            "subreddit_id": "t5_2s3qj",
            "banned_by": null,
            "link_id": "t3_2i87e4",
            "likes": null,
            "replies": "",
            "user_reports": [],
            "saved": false,
            "id": "ckzzmt2",
            "gilded": 0,
            "report_reasons": null,
            "author": "doizernasty",
            "parent_id": "t3_2i87e4",
            "score": 2,
            "approved_by": null,
            "controversiality": 0,
            "body": "Same. Tried everything, it's disappointing.",
            "edited": false,
            "author_flair_css_class": null,
            "downs": 0,
            "body_html": "&lt;div class=\"md\"&gt;&lt;p&gt;Same. Tried everything, it&amp;#39;s disappointing.&lt;/p&gt;\n&lt;/div&gt;",
            "subreddit": "Bitcoin",
            "score_hidden": false,
            "name": "t1_ckzzmt2",
            "created": 1412425486,
            "author_flair_text": null,
            "created_utc": 1412396686,
            "distinguished": null,
            "mod_reports": [],
            "num_reports": null,
            "ups": 2
          }
        },
        {
          "kind": "t1",
          "data": {
            "subreddit_id": "t5_2s3qj",
            "banned_by": null,
            "link_id": "t3_2i87e4",
            "likes": null,
            "replies": "",
            "user_reports": [],
            "saved": false,
            "id": "ckztiyb",
            "gilded": 0,
            "report_reasons": null,
            "author": "TruValueCapital",
            "parent_id": "t3_2i87e4",
            "score": 0,
            "approved_by": null,
            "controversiality": 0,
            "body": "Their service works perfect and its all Free - I cannot complain.",
            "edited": false,
            "author_flair_css_class": null,
            "downs": 0,
            "body_html": "&lt;div class=\"md\"&gt;&lt;p&gt;Their service works perfect and its all Free - I cannot complain.&lt;/p&gt;\n&lt;/div&gt;",
            "subreddit": "Bitcoin",
            "score_hidden": false,
            "name": "t1_ckztiyb",
            "created": 1412408657,
            "author_flair_text": null,
            "created_utc": 1412379857,
            "distinguished": null,
            "mod_reports": [],
            "num_reports": null,
            "ups": 0
          }
        }
      ],
      "after": null,
      "before": null
    }
  }
]