[
  {
    "kind": "Listing",
    "data": {
      "modhash": "",
      "children": [
        {
          "kind": "t3",
          "data": {
            "domain": "youtube.com",
            "banned_by": null,
            "media_embed": {
              "content": "&lt;iframe class=\"embedly-embed\" src=\"//cdn.embedly.com/widgets/media.html?src=http%3A%2F%2Fwww.youtube.com%2Fembed%2FSqjoSfDKnEQ%3Ffeature%3Doembed&amp;url=http%3A%2F%2Fwww.youtube.com%2Fwatch%3Fv%3DSqjoSfDKnEQ&amp;image=http%3A%2F%2Fi.ytimg.com%2Fvi%2FSqjoSfDKnEQ%2Fhqdefault.jpg&amp;key=2aa3c4d5f3de4f5b9120b660ad850dc9&amp;type=text%2Fhtml&amp;schema=youtube\" width=\"600\" height=\"338\" scrolling=\"no\" frameborder=\"0\" allowfullscreen&gt;&lt;/iframe&gt;",
              "width": 600,
              "scrolling": false,
              "height": 338
            },
            "subreddit": "Bitcoin",
            "selftext_html": null,
            "selftext": "",
            "likes": null,
            "user_reports": [],
            "secure_media": {
              "oembed": {
                "provider_url": "http://www.youtube.com/",
                "description": "Hacking, according to the 1985 film Weird Science (© Universal Studios)",
                "title": "Weird Science Hacking Scene",
                "url": "http://www.youtube.com/watch?v=SqjoSfDKnEQ",
                "type": "video",
                "author_name": "woowoo678",
                "height": 338,
                "width": 600,
                "html": "&lt;iframe class=\"embedly-embed\" src=\"https://cdn.embedly.com/widgets/media.html?src=https%3A%2F%2Fwww.youtube.com%2Fembed%2FSqjoSfDKnEQ%3Ffeature%3Doembed&amp;url=http%3A%2F%2Fwww.youtube.com%2Fwatch%3Fv%3DSqjoSfDKnEQ&amp;image=http%3A%2F%2Fi.ytimg.com%2Fvi%2FSqjoSfDKnEQ%2Fhqdefault.jpg&amp;key=2aa3c4d5f3de4f5b9120b660ad850dc9&amp;type=text%2Fhtml&amp;schema=youtube\" width=\"600\" height=\"338\" scrolling=\"no\" frameborder=\"0\" allowfullscreen&gt;&lt;/iframe&gt;",
                "thumbnail_width": 480,
                "version": "1.0",
                "provider_name": "YouTube",
                "thumbnail_url": "https://i.embed.ly/1/image?url=http%3A%2F%2Fi.ytimg.com%2Fvi%2FSqjoSfDKnEQ%2Fhqdefault.jpg&amp;key=b1e305db91cf4aa5a86b732cc9fffceb",
                "thumbnail_height": 360,
                "author_url": "http://www.youtube.com/user/woowoo678"
              },
              "type": "youtube.com"
            },
            "link_flair_text": null,
            "id": "2i8bf9",
            "gilded": 0,
            "secure_media_embed": {
              "content": "&lt;iframe class=\"embedly-embed\" src=\"https://cdn.embedly.com/widgets/media.html?src=https%3A%2F%2Fwww.youtube.com%2Fembed%2FSqjoSfDKnEQ%3Ffeature%3Doembed&amp;url=http%3A%2F%2Fwww.youtube.com%2Fwatch%3Fv%3DSqjoSfDKnEQ&amp;image=http%3A%2F%2Fi.ytimg.com%2Fvi%2FSqjoSfDKnEQ%2Fhqdefault.jpg&amp;key=2aa3c4d5f3de4f5b9120b660ad850dc9&amp;type=text%2Fhtml&amp;schema=youtube\" width=\"600\" height=\"338\" scrolling=\"no\" frameborder=\"0\" allowfullscreen&gt;&lt;/iframe&gt;",
              "width": 600,
              "scrolling": false,
              "height": 338
            },
            "clicked": false,
            "report_reasons": null,
            "author": "CP70",
            "media": {
              "oembed": {
                "provider_url": "http://www.youtube.com/",
                "description": "Hacking, according to the 1985 film Weird Science (© Universal Studios)",
                "title": "Weird Science Hacking Scene",
                "url": "http://www.youtube.com/watch?v=SqjoSfDKnEQ",
                "type": "video",
                "author_name": "woowoo678",
                "height": 338,
                "width": 600,
                "html": "&lt;iframe class=\"embedly-embed\" src=\"//cdn.embedly.com/widgets/media.html?src=http%3A%2F%2Fwww.youtube.com%2Fembed%2FSqjoSfDKnEQ%3Ffeature%3Doembed&amp;url=http%3A%2F%2Fwww.youtube.com%2Fwatch%3Fv%3DSqjoSfDKnEQ&amp;image=http%3A%2F%2Fi.ytimg.com%2Fvi%2FSqjoSfDKnEQ%2Fhqdefault.jpg&amp;key=2aa3c4d5f3de4f5b9120b660ad850dc9&amp;type=text%2Fhtml&amp;schema=youtube\" width=\"600\" height=\"338\" scrolling=\"no\" frameborder=\"0\" allowfullscreen&gt;&lt;/iframe&gt;",
                "thumbnail_width": 480,
                "version": "1.0",
                "provider_name": "YouTube",
                "thumbnail_url": "http://i.ytimg.com/vi/SqjoSfDKnEQ/hqdefault.jpg",
                "thumbnail_height": 360,
                "author_url": "http://www.youtube.com/user/woowoo678"
              },
              "type": "youtube.com"
            },
            "score": 5,
            "approved_by": null,
            "over_18": false,
            "hidden": false,
            "thumbnail": "http://b.thumbs.redditmedia.com/Xr7-YS2Lm2QX8LqmdHEtdTJQFjV3kIl4k--4NmyLe_M.jpg",
            "subreddit_id": "t5_2s3qj",
            "edited": false,
            "link_flair_css_class": null,
            "author_flair_css_class": null,
            "downs": 0,
            "mod_reports": [],
            "saved": false,
            "is_self": false,
            "name": "t3_2i8bf9",
            "permalink": "/r/Bitcoin/comments/2i8bf9/the_problem_is_its_a_lame_idea_okay/",
            "stickied": false,
            "created": 1412405033,
            "url": "https://www.youtube.com/watch?v=SqjoSfDKnEQ",
            "author_flair_text": null,
            "title": "The problem is, it's a lame idea okay?",
            "created_utc": 1412376233,
            "ups": 5,
            "upvote_ratio": 0.78,
            "num_comments": 5,
            "visited": false,
            "num_reports": null,
            "distinguished": null
          }
        }
      ],
      "after": null,
      "before": null
    }
  },
  {
    "kind": "Listing",
    "data": {
      "modhash": "",
      "children": [
        {
          "kind": "t1",
          "data": {
            "subreddit_id": "t5_2s3qj",
            "banned_by": null,
            "link_id": "t3_2i8bf9",
            "likes": null,
            "replies": "",
            "user_reports": [],
            "saved": false,
            "id": "ckzvums",
            "gilded": 0,
            "report_reasons": null,
            "author": "efxco",
            "parent_id": "t3_2i8bf9",
            "score": 1,
            "approved_by": null,
            "controversiality": 0,
            "body": "i'm just puked, really, there's a food on my carpet. Cool vid if you want to puke.",
            "edited": false,
            "author_flair_css_class": null,
            "downs": 0,
            "body_html": "&lt;div class=\"md\"&gt;&lt;p&gt;i&amp;#39;m just puked, really, there&amp;#39;s a food on my carpet. Cool vid if you want to puke.&lt;/p&gt;\n&lt;/div&gt;",
            "subreddit": "Bitcoin",
            "score_hidden": false,
            "name": "t1_ckzvums",
            "created": 1412414703,
            "author_flair_text": null,
            "created_utc": 1412385903,
            "distinguished": null,
            "mod_reports": [],
            "num_reports": null,
            "ups": 1
          }
        },
        {
          "kind": "t1",
          "data": {
            "subreddit_id": "t5_2s3qj",
            "banned_by": null,
            "link_id": "t3_2i8bf9",
            "likes": null,
            "replies": "",
            "user_reports": [],
            "saved": false,
            "id": "ckzy6aq",
            "gilded": 0,
            "report_reasons": null,
            "author": "Teph87",
            "parent_id": "t3_2i8bf9",
            "score": 1,
            "approved_by": null,
            "controversiality": 0,
            "body": "That's what the block chain actually looks like",
            "edited": false,
            "author_flair_css_class": null,
            "downs": 0,
            "body_html": "&lt;div class=\"md\"&gt;&lt;p&gt;That&amp;#39;s what the block chain actually looks like&lt;/p&gt;\n&lt;/div&gt;",
            "subreddit": "Bitcoin",
            "score_hidden": false,
            "name": "t1_ckzy6aq",
            "created": 1412421038,
            "author_flair_text": null,
            "created_utc": 1412392238,
            "distinguished": null,
            "mod_reports": [],
            "num_reports": null,
            "ups": 1
          }
        },
        {
          "kind": "t1",
          "data": {
            "subreddit_id": "t5_2s3qj",
            "banned_by": null,
            "link_id": "t3_2i8bf9",
            "likes": null,
            "replies": "",
            "user_reports": [],
            "saved": false,
            "id": "ckzzbmt",
            "gilded": 0,
            "report_reasons": null,
            "author": "pizzaface18",
            "parent_id": "t3_2i8bf9",
            "score": 1,
            "approved_by": null,
            "controversiality": 0,
            "body": "80s movies!!",
            "edited": false,
            "author_flair_css_class": null,
            "downs": 0,
            "body_html": "&lt;div class=\"md\"&gt;&lt;p&gt;80s movies!!&lt;/p&gt;\n&lt;/div&gt;",
            "subreddit": "Bitcoin",
            "score_hidden": false,
            "name": "t1_ckzzbmt",
            "created": 1412424505,
            "author_flair_text": null,
            "created_utc": 1412395705,
            "distinguished": null,
            "mod_reports": [],
            "num_reports": null,
            "ups": 1
          }
        },
        {
          "kind": "t1",
          "data": {
            "subreddit_id": "t5_2s3qj",
            "banned_by": null,
            "link_id": "t3_2i8bf9",
            "likes": null,
            "replies": "",
            "user_reports": [],
            "saved": false,
            "id": "cl02ygo",
            "gilded": 0,
            "report_reasons": null,
            "author": "TheSelfGoverned",
            "parent_id": "t3_2i8bf9",
            "score": 1,
            "approved_by": null,
            "controversiality": 0,
            "body": "When someone asks how bitcoin mining works, I send them this clip.",
            "edited": false,
            "author_flair_css_class": null,
            "downs": 0,
            "body_html": "&lt;div class=\"md\"&gt;&lt;p&gt;When someone asks how bitcoin mining works, I send them this clip.&lt;/p&gt;\n&lt;/div&gt;",
            "subreddit": "Bitcoin",
            "score_hidden": false,
            "name": "t1_cl02ygo",
            "created": 1412439604,
            "author_flair_text": null,
            "created_utc": 1412410804,
            "distinguished": null,
            "mod_reports": [],
            "num_reports": null,
            "ups": 1
          }
        },
        {
          "kind": "t1",
          "data": {
            "subreddit_id": "t5_2s3qj",
            "banned_by": null,
            "link_id": "t3_2i8bf9",
            "likes": null,
            "replies": "",
            "user_reports": [],
            "saved": false,
            "id": "cl09c1r",
            "gilded": 0,
            "report_reasons": null,
            "author": "BitcoinIsSimple",
            "parent_id": "t3_2i8bf9",
            "score": 1,
            "approved_by": null,
            "controversiality": 0,
            "body": "Hodl lame ideas. ",
            "edited": false,
            "author_flair_css_class": null,
            "downs": 0,
            "body_html": "&lt;div class=\"md\"&gt;&lt;p&gt;Hodl lame ideas. &lt;/p&gt;\n&lt;/div&gt;",
            "subreddit": "Bitcoin",
            "score_hidden": false,
            "name": "t1_cl09c1r",
            "created": 1412467931,
            "author_flair_text": null,
            "created_utc": 1412439131,
            "distinguished": null,
            "mod_reports": [],
            "num_reports": null,
            "ups": 1
          }
        }
      ],
      "after": null,
      "before": null
    }
  }
]