[
  {
    "kind": "Listing",
    "data": {
      "modhash": "",
      "children": [
        {
          "kind": "t3",
          "data": {
            "domain": "self.Bitcoin",
            "banned_by": null,
            "media_embed": {},
            "subreddit": "Bitcoin",
            "selftext_html": "&lt;!-- SC_OFF --&gt;&lt;div class=\"md\"&gt;&lt;p&gt;Few days ago Max Keiser started telling people to sell Bitcoin all their bitcoin and buy Startcoin. Whoever did this as making huge profits. Very weird it&amp;#39;s almost as if he knows something. &lt;/p&gt;\n&lt;/div&gt;&lt;!-- SC_ON --&gt;",
            "selftext": "Few days ago Max Keiser started telling people to sell Bitcoin all their bitcoin and buy Startcoin. Whoever did this as making huge profits. Very weird it's almost as if he knows something. ",
            "likes": null,
            "user_reports": [],
            "secure_media": null,
            "link_flair_text": null,
            "id": "2ifab0",
            "gilded": 0,
            "secure_media_embed": {},
            "clicked": false,
            "report_reasons": null,
            "author": "bitLeap",
            "media": null,
            "score": 0,
            "approved_by": null,
            "over_18": false,
            "hidden": false,
            "thumbnail": "self",
            "subreddit_id": "t5_2s3qj",
            "edited": false,
            "link_flair_css_class": null,
            "author_flair_css_class": null,
            "downs": 0,
            "mod_reports": [],
            "saved": false,
            "is_self": true,
            "name": "t3_2ifab0",
            "permalink": "/r/Bitcoin/comments/2ifab0/max_told_people_to_ditch_bitcoin_for_start/",
            "stickied": false,
            "created": 1412603215,
            "url": "http://www.reddit.com/r/Bitcoin/comments/2ifab0/max_told_people_to_ditch_bitcoin_for_start/",
            "author_flair_text": null,
            "title": "Max told people to ditch Bitcoin for START",
            "created_utc": 1412574415,
            "ups": 0,
            "upvote_ratio": 0.21,
            "num_comments": 12,
            "visited": false,
            "num_reports": null,
            "distinguished": null
          }
        }
      ],
      "after": null,
      "before": null
    }
  },
  {
    "kind": "Listing",
    "data": {
      "modhash": "",
      "children": [
        {
          "kind": "t1",
          "data": {
            "subreddit_id": "t5_2s3qj",
            "banned_by": null,
            "link_id": "t3_2ifab0",
            "likes": null,
            "replies": {
              "kind": "Listing",
              "data": {
                "modhash": "",
                "children": [
                  {
                    "kind": "t1",
                    "data": {
                      "subreddit_id": "t5_2s3qj",
                      "banned_by": null,
                      "link_id": "t3_2ifab0",
                      "likes": null,
                      "replies": {
                        "kind": "Listing",
                        "data": {
                          "modhash": "",
                          "children": [
                            {
                              "kind": "t1",
                              "data": {
                                "subreddit_id": "t5_2s3qj",
                                "banned_by": null,
                                "link_id": "t3_2ifab0",
                                "likes": null,
                                "replies": {
                                  "kind": "Listing",
                                  "data": {
                                    "modhash": "",
                                    "children": [
                                      {
                                        "kind": "t1",
                                        "data": {
                                          "subreddit_id": "t5_2s3qj",
                                          "banned_by": null,
                                          "link_id": "t3_2ifab0",
                                          "likes": null,
                                          "replies": {
                                            "kind": "Listing",
                                            "data": {
                                              "modhash": "",
                                              "children": [
                                                {
                                                  "kind": "t1",
                                                  "data": {
                                                    "subreddit_id": "t5_2s3qj",
                                                    "banned_by": null,
                                                    "link_id": "t3_2ifab0",
                                                    "likes": null,
                                                    "replies": "",
                                                    "user_reports": [],
                                                    "saved": false,
                                                    "id": "cl1pjhg",
                                                    "gilded": 0,
                                                    "report_reasons": null,
                                                    "author": "utuxia",
                                                    "parent_id": "t1_cl1p6h2",
                                                    "score": 2,
                                                    "approved_by": null,
                                                    "controversiality": 0,
                                                    "body": "I am not doubting your belief in SMARTcoin, but do you know how many times I've seen this before?",
                                                    "edited": false,
                                                    "author_flair_css_class": null,
                                                    "downs": 0,
                                                    "body_html": "&lt;div class=\"md\"&gt;&lt;p&gt;I am not doubting your belief in SMARTcoin, but do you know how many times I&amp;#39;ve seen this before?&lt;/p&gt;\n&lt;/div&gt;",
                                                    "subreddit": "Bitcoin",
                                                    "score_hidden": false,
                                                    "name": "t1_cl1pjhg",
                                                    "created": 1412607562,
                                                    "author_flair_text": null,
                                                    "created_utc": 1412578762,
                                                    "distinguished": null,
                                                    "mod_reports": [],
                                                    "num_reports": null,
                                                    "ups": 2
                                                  }
                                                }
                                              ],
                                              "after": null,
                                              "before": null
                                            }
                                          },
                                          "user_reports": [],
                                          "saved": false,
                                          "id": "cl1p6h2",
                                          "gilded": 0,
                                          "report_reasons": null,
                                          "author": "bitLeap",
                                          "parent_id": "t1_cl1p3pt",
                                          "score": 1,
                                          "approved_by": null,
                                          "controversiality": 0,
                                          "body": "That was a completely different scenario there he was endorsing it's potential but Startcoin is a different ballgame it's a done deal he's telling people it's the REAL DEAL. So far he is right and people are finding a way to protect against what's happening to Bitcoin I include myself in that group. ",
                                          "edited": false,
                                          "author_flair_css_class": null,
                                          "downs": 0,
                                          "body_html": "&lt;div class=\"md\"&gt;&lt;p&gt;That was a completely different scenario there he was endorsing it&amp;#39;s potential but Startcoin is a different ballgame it&amp;#39;s a done deal he&amp;#39;s telling people it&amp;#39;s the REAL DEAL. So far he is right and people are finding a way to protect against what&amp;#39;s happening to Bitcoin I include myself in that group. &lt;/p&gt;\n&lt;/div&gt;",
                                          "subreddit": "Bitcoin",
                                          "score_hidden": false,
                                          "name": "t1_cl1p6h2",
                                          "created": 1412605952,
                                          "author_flair_text": null,
                                          "created_utc": 1412577152,
                                          "ups": 1,
                                          "mod_reports": [],
                                          "num_reports": null,
                                          "distinguished": null
                                        }
                                      }
                                    ],
                                    "after": null,
                                    "before": null
                                  }
                                },
                                "user_reports": [],
                                "saved": false,
                                "id": "cl1p3pt",
                                "gilded": 0,
                                "report_reasons": null,
                                "author": "utuxia",
                                "parent_id": "t1_cl1osom",
                                "score": 2,
                                "approved_by": null,
                                "controversiality": 0,
                                "body": "I got nothing against Max. He's a bit trollish for my tastes....but he did advise everyone to buy Quarkcoin. I'm just asking, what was the price then and what is it now?\n\nhttps://bitcoinwisdom.com/markets/cryptsy/qrkbtc see 1W chart",
                                "edited": false,
                                "author_flair_css_class": null,
                                "downs": 0,
                                "body_html": "&lt;div class=\"md\"&gt;&lt;p&gt;I got nothing against Max. He&amp;#39;s a bit trollish for my tastes....but he did advise everyone to buy Quarkcoin. I&amp;#39;m just asking, what was the price then and what is it now?&lt;/p&gt;\n\n&lt;p&gt;&lt;a href=\"https://bitcoinwisdom.com/markets/cryptsy/qrkbtc\"&gt;https://bitcoinwisdom.com/markets/cryptsy/qrkbtc&lt;/a&gt; see 1W chart&lt;/p&gt;\n&lt;/div&gt;",
                                "subreddit": "Bitcoin",
                                "score_hidden": false,
                                "name": "t1_cl1p3pt",
                                "created": 1412605626,
                                "author_flair_text": null,
                                "created_utc": 1412576826,
                                "distinguished": null,
                                "mod_reports": [],
                                "num_reports": null,
                                "ups": 2
                              }
                            }
                          ],
                          "after": null,
                          "before": null
                        }
                      },
                      "user_reports": [],
                      "saved": false,
                      "id": "cl1osom",
                      "gilded": 0,
                      "report_reasons": null,
                      "author": "bitLeap",
                      "parent_id": "t1_cl1ojse",
                      "score": 1,
                      "approved_by": null,
                      "controversiality": 0,
                      "body": "Well with all due respect I don't care what you think of him what I care are the results and Max was the driving force behind Bitcoin for many years and START is doing what he said it would do just like when he said back 2010 what bitcoin would eventually do.",
                      "edited": false,
                      "author_flair_css_class": null,
                      "downs": 0,
                      "body_html": "&lt;div class=\"md\"&gt;&lt;p&gt;Well with all due respect I don&amp;#39;t care what you think of him what I care are the results and Max was the driving force behind Bitcoin for many years and START is doing what he said it would do just like when he said back 2010 what bitcoin would eventually do.&lt;/p&gt;\n&lt;/div&gt;",
                      "subreddit": "Bitcoin",
                      "score_hidden": false,
                      "name": "t1_cl1osom",
                      "created": 1412604382,
                      "author_flair_text": null,
                      "created_utc": 1412575582,
                      "ups": 1,
                      "mod_reports": [],
                      "num_reports": null,
                      "distinguished": null
                    }
                  }
                ],
                "after": null,
                "before": null
              }
            },
            "user_reports": [],
            "saved": false,
            "id": "cl1ojse",
            "gilded": 0,
            "report_reasons": null,
            "author": "utuxia",
            "parent_id": "t3_2ifab0",
            "score": 6,
            "approved_by": null,
            "controversiality": 0,
            "body": "He said the same thing with Quarkcoin. How is that advise fairing these days?",
            "edited": false,
            "author_flair_css_class": null,
            "downs": 0,
            "body_html": "&lt;div class=\"md\"&gt;&lt;p&gt;He said the same thing with Quarkcoin. How is that advise fairing these days?&lt;/p&gt;\n&lt;/div&gt;",
            "subreddit": "Bitcoin",
            "score_hidden": false,
            "name": "t1_cl1ojse",
            "created": 1412603442,
            "author_flair_text": null,
            "created_utc": 1412574642,
            "distinguished": null,
            "mod_reports": [],
            "num_reports": null,
            "ups": 6
          }
        },
        {
          "kind": "t1",
          "data": {
            "subreddit_id": "t5_2s3qj",
            "banned_by": null,
            "link_id": "t3_2ifab0",
            "likes": null,
            "replies": "",
            "user_reports": [],
            "saved": false,
            "id": "cl1pbbx",
            "gilded": 0,
            "report_reasons": null,
            "author": "NoGooderr",
            "parent_id": "t3_2ifab0",
            "score": 3,
            "approved_by": null,
            "controversiality": 0,
            "body": "Another shitcoin pump? ugh... lol",
            "edited": false,
            "author_flair_css_class": null,
            "downs": 0,
            "body_html": "&lt;div class=\"md\"&gt;&lt;p&gt;Another shitcoin pump? ugh... lol&lt;/p&gt;\n&lt;/div&gt;",
            "subreddit": "Bitcoin",
            "score_hidden": false,
            "name": "t1_cl1pbbx",
            "created": 1412606535,
            "author_flair_text": null,
            "created_utc": 1412577735,
            "distinguished": null,
            "mod_reports": [],
            "num_reports": null,
            "ups": 3
          }
        },
        {
          "kind": "t1",
          "data": {
            "subreddit_id": "t5_2s3qj",
            "banned_by": null,
            "link_id": "t3_2ifab0",
            "likes": null,
            "replies": {
              "kind": "Listing",
              "data": {
                "modhash": "",
                "children": [
                  {
                    "kind": "t1",
                    "data": {
                      "subreddit_id": "t5_2s3qj",
                      "banned_by": null,
                      "link_id": "t3_2ifab0",
                      "likes": null,
                      "replies": "",
                      "user_reports": [],
                      "saved": false,
                      "id": "cl1or4h",
                      "gilded": 0,
                      "report_reasons": null,
                      "author": "bitLeap",
                      "parent_id": "t1_cl1okjx",
                      "score": 1,
                      "approved_by": null,
                      "controversiality": 0,
                      "body": "He puts Startcoin way above bitcoin\nhttps://twitter.com/maxkeiser/status/518698334283132928\n\nAnd goes on to call it the eight wonder of the world!\nhttps://twitter.com/maxkeiser/status/518732471639478272",
                      "edited": 1412575826,
                      "author_flair_css_class": null,
                      "downs": 0,
                      "body_html": "&lt;div class=\"md\"&gt;&lt;p&gt;He puts Startcoin way above bitcoin\n&lt;a href=\"https://twitter.com/maxkeiser/status/518698334283132928\"&gt;https://twitter.com/maxkeiser/status/518698334283132928&lt;/a&gt;&lt;/p&gt;\n\n&lt;p&gt;And goes on to call it the eight wonder of the world!\n&lt;a href=\"https://twitter.com/maxkeiser/status/518732471639478272\"&gt;https://twitter.com/maxkeiser/status/518732471639478272&lt;/a&gt;&lt;/p&gt;\n&lt;/div&gt;",
                      "subreddit": "Bitcoin",
                      "score_hidden": false,
                      "name": "t1_cl1or4h",
                      "created": 1412604221,
                      "author_flair_text": null,
                      "created_utc": 1412575421,
                      "ups": 1,
                      "mod_reports": [],
                      "num_reports": null,
                      "distinguished": null
                    }
                  }
                ],
                "after": null,
                "before": null
              }
            },
            "user_reports": [],
            "saved": false,
            "id": "cl1okjx",
            "gilded": 0,
            "report_reasons": null,
            "author": "ParsnipCommander",
            "parent_id": "t3_2ifab0",
            "score": 2,
            "approved_by": null,
            "controversiality": 0,
            "body": "Uh no. He just said this on twitter in the last 24 hours: \"I'm organizing a delegation to travel to Kremlin to pitch Bitcoin and crypto. I feel that if properly educated, Russia would embrace BTC.\" \nhttps://twitter.com/maxkeiser/status/518733290094997505\n\nAlso Startcoin is a crowd funding thing - doesn't compete at all with Bitcoin\n\nWhat is your source? ",
            "edited": false,
            "author_flair_css_class": null,
            "downs": 0,
            "body_html": "&lt;div class=\"md\"&gt;&lt;p&gt;Uh no. He just said this on twitter in the last 24 hours: &amp;quot;I&amp;#39;m organizing a delegation to travel to Kremlin to pitch Bitcoin and crypto. I feel that if properly educated, Russia would embrace BTC.&amp;quot; \n&lt;a href=\"https://twitter.com/maxkeiser/status/518733290094997505\"&gt;https://twitter.com/maxkeiser/status/518733290094997505&lt;/a&gt;&lt;/p&gt;\n\n&lt;p&gt;Also Startcoin is a crowd funding thing - doesn&amp;#39;t compete at all with Bitcoin&lt;/p&gt;\n\n&lt;p&gt;What is your source? &lt;/p&gt;\n&lt;/div&gt;",
            "subreddit": "Bitcoin",
            "score_hidden": false,
            "name": "t1_cl1okjx",
            "created": 1412603522,
            "author_flair_text": null,
            "created_utc": 1412574722,
            "distinguished": null,
            "mod_reports": [],
            "num_reports": null,
            "ups": 2
          }
        },
        {
          "kind": "t1",
          "data": {
            "subreddit_id": "t5_2s3qj",
            "banned_by": null,
            "link_id": "t3_2ifab0",
            "likes": null,
            "replies": "",
            "user_reports": [],
            "saved": false,
            "id": "cl1p5jj",
            "gilded": 0,
            "report_reasons": null,
            "author": "bitcoinrole",
            "parent_id": "t3_2ifab0",
            "score": 1,
            "approved_by": null,
            "controversiality": 0,
            "body": "https://bitcointalk.org/index.php?topic=651307.0\n\n&gt; Smells like new Keiser coin ...",
            "edited": false,
            "author_flair_css_class": null,
            "downs": 0,
            "body_html": "&lt;div class=\"md\"&gt;&lt;p&gt;&lt;a href=\"https://bitcointalk.org/index.php?topic=651307.0\"&gt;https://bitcointalk.org/index.php?topic=651307.0&lt;/a&gt;&lt;/p&gt;\n\n&lt;blockquote&gt;\n&lt;p&gt;Smells like new Keiser coin ...&lt;/p&gt;\n&lt;/blockquote&gt;\n&lt;/div&gt;",
            "subreddit": "Bitcoin",
            "score_hidden": false,
            "name": "t1_cl1p5jj",
            "created": 1412605841,
            "author_flair_text": null,
            "created_utc": 1412577041,
            "distinguished": null,
            "mod_reports": [],
            "num_reports": null,
            "ups": 1
          }
        },
        {
          "kind": "t1",
          "data": {
            "subreddit_id": "t5_2s3qj",
            "banned_by": null,
            "link_id": "t3_2ifab0",
            "likes": null,
            "replies": {
              "kind": "Listing",
              "data": {
                "modhash": "",
                "children": [
                  {
                    "kind": "t1",
                    "data": {
                      "subreddit_id": "t5_2s3qj",
                      "banned_by": null,
                      "link_id": "t3_2ifab0",
                      "likes": null,
                      "replies": {
                        "kind": "Listing",
                        "data": {
                          "modhash": "",
                          "children": [
                            {
                              "kind": "t1",
                              "data": {
                                "subreddit_id": "t5_2s3qj",
                                "banned_by": null,
                                "link_id": "t3_2ifab0",
                                "likes": null,
                                "replies": "",
                                "user_reports": [],
                                "saved": false,
                                "id": "cl1pqof",
                                "gilded": 0,
                                "report_reasons": null,
                                "author": "a4537389",
                                "parent_id": "t1_cl1pe28",
                                "score": 0,
                                "approved_by": null,
                                "controversiality": 0,
                                "body": "StartCoins held on StartJoin pays compounded interest. As someone posted the link Max called StartCoin the real revolution in crypto-money. I don't think he would put his life reputation on the line if he didn't know what he's talking about. (haters will sink hating)",
                                "edited": false,
                                "author_flair_css_class": null,
                                "downs": 0,
                                "body_html": "&lt;div class=\"md\"&gt;&lt;p&gt;StartCoins held on StartJoin pays compounded interest. As someone posted the link Max called StartCoin the real revolution in crypto-money. I don&amp;#39;t think he would put his life reputation on the line if he didn&amp;#39;t know what he&amp;#39;s talking about. (haters will sink hating)&lt;/p&gt;\n&lt;/div&gt;",
                                "subreddit": "Bitcoin",
                                "score_hidden": false,
                                "name": "t1_cl1pqof",
                                "created": 1412608532,
                                "author_flair_text": null,
                                "created_utc": 1412579732,
                                "distinguished": null,
                                "mod_reports": [],
                                "num_reports": null,
                                "ups": 0
                              }
                            }
                          ],
                          "after": null,
                          "before": null
                        }
                      },
                      "user_reports": [],
                      "saved": false,
                      "id": "cl1pe28",
                      "gilded": 0,
                      "report_reasons": null,
                      "author": "reddbullish",
                      "parent_id": "t1_cl1p3qb",
                      "score": 2,
                      "approved_by": null,
                      "controversiality": 0,
                      "body": "&gt; I'm still being payed compound interest holding at startjoin \n\nPlease explain.",
                      "edited": false,
                      "author_flair_css_class": null,
                      "downs": 0,
                      "body_html": "&lt;div class=\"md\"&gt;&lt;blockquote&gt;\n&lt;p&gt;I&amp;#39;m still being payed compound interest holding at startjoin &lt;/p&gt;\n&lt;/blockquote&gt;\n\n&lt;p&gt;Please explain.&lt;/p&gt;\n&lt;/div&gt;",
                      "subreddit": "Bitcoin",
                      "score_hidden": false,
                      "name": "t1_cl1pe28",
                      "created": 1412606869,
                      "author_flair_text": null,
                      "created_utc": 1412578069,
                      "ups": 2,
                      "mod_reports": [],
                      "num_reports": null,
                      "distinguished": null
                    }
                  }
                ],
                "after": null,
                "before": null
              }
            },
            "user_reports": [],
            "saved": false,
            "id": "cl1p3qb",
            "gilded": 0,
            "report_reasons": null,
            "author": "a4537389",
            "parent_id": "t3_2ifab0",
            "score": 1,
            "approved_by": null,
            "controversiality": 0,
            "body": "Yep I did take advantage of that. I was down almost 6k dollars and now I'm up 20k dollars. Sold all my BTC for Start and I'm still being payed compound interest holding at startjoin :). Max is the real deal!",
            "edited": false,
            "author_flair_css_class": null,
            "downs": 0,
            "body_html": "&lt;div class=\"md\"&gt;&lt;p&gt;Yep I did take advantage of that. I was down almost 6k dollars and now I&amp;#39;m up 20k dollars. Sold all my BTC for Start and I&amp;#39;m still being payed compound interest holding at startjoin :). Max is the real deal!&lt;/p&gt;\n&lt;/div&gt;",
            "subreddit": "Bitcoin",
            "score_hidden": false,
            "name": "t1_cl1p3qb",
            "created": 1412605627,
            "author_flair_text": null,
            "created_utc": 1412576827,
            "distinguished": null,
            "mod_reports": [],
            "num_reports": null,
            "ups": 1
          }
        }
      ],
      "after": null,
      "before": null
    }
  }
]